{"speaker": "President.", "english": "President. The next item is the report ( A6-0031/2006 ) by Jean Louis Cottigny, on behalf of the Committee on Employment and Social Affairs, on restructuring and employment ( 2005/2188(INI) ).", "lang": "EN", "original": "President. The next item is the report ( A6-0031/2006 ) by Jean Louis Cottigny, on behalf of the Committee on Employment and Social Affairs, on restructuring and employment ( 2005/2188(INI) ).", "agenda_item": "Restructuring and employment (debate)", "debate_id": "CRE-20060314-ITEM-006", "intervention_id": "2-028"}